{"title": "Resultados positivos revalorizan la medicina tradicional china frente a Covid-19", "author": null, "url": "https://dialogosdelsur.operamundi.uol.com.br/permalink/63977", "hostname": "operamundi.uol.com.br", "description": "La MTC ya es parte del protocolo de prevenci\u00f3n, control y tratamiento de la Covid-19 en China y ahora el pa\u00eds comparte con la comunidad internacional", "sitename": null, "date": "2020-04-06", "id": null, "license": null, "body": null, "comments": "", "commentsbody": null, "raw_text": null, "text": "Resultados positivos revalorizan la medicina tradicional china frente a Covid-19\nLa MTC ya es parte del protocolo de prevenci\u00f3n, control y tratamiento de la Covid-19 en China y ahora el pa\u00eds comparte con la comunidad internacional\nSalvar las vidas amenazadas por la Covid-19 es un desaf\u00edo que obliga a innovar terapias con productos existentes en el mercado mientras llega alguna vacuna, y en ese proceso China recurri\u00f3 a uno de sus tesoros milenarios: la medicina tradicional (MTC).\nLa propagaci\u00f3n mundial de la mort\u00edfera neumon\u00eda, causada por el coronavirus SARS-CoV-2, tiene a la comunidad cient\u00edfica en una carrera sin descanso tras la cura que, para ser realmente segura, requiere tiempo con vistas a investigar y comprobar a fondo su efectividad.\nAl ser el primer pa\u00eds afectado, China activ\u00f3 la b\u00fasqueda de una inyecci\u00f3n propia y de conjunto compil\u00f3 una treintena de f\u00e1rmacos occidentales con potencial para tratar a los enfermos y evitar complicaciones letales de la patolog\u00eda.\nEntre los escogidos figuran el fosfato de cloroquina, empleado contra la malaria; el remdesivir, creado para combatir el \u00e9bola; el antiviral japon\u00e9s favipiravir y derivados del plasma sangu\u00edneo donado por pacientes recuperados.\nPero de acuerdo con expertos del gigante asi\u00e1tico, esos y otros productos demostraron mejor desempe\u00f1o y ayudaron a un significativo n\u00famero de contagiados a rebasar la neumon\u00eda, al combinarlos con recetas de la MTC.\nEspec\u00edficamente notaron los beneficios de las f\u00f3rmulas herbolarias para combatir s\u00edntomas cl\u00ednicos como fiebre alta, tos, p\u00e9rdida de apetito, n\u00e1useas, diarreas, problemas respiratorios y fatiga.\nPrensa Latina\nTCM ya forma parte del protocolo de prevenci\u00f3n, control y tratamiento de Covid-19 en China\nLos resultados conllevaron al Gobierno a movilizar casi cinco mil galenos de esa especialidad hacia la provincia Hubei y su capital Wuhan -epicentro del brote de Covid-19- para apoyar la lucha epidemiol\u00f3gica en el momento m\u00e1s \u00e1lgido de la crisis.\nLa ciudad tuvo un hospital de campa\u00f1a, el Jiangxia, dedicado solo a la MTC y en sus 26 d\u00edas de operaciones cur\u00f3 a 392 de las casi 600 personas ingresadas y traslad\u00f3 el resto a otras instalaciones.\nAll\u00ed se administraron infusiones herbales seg\u00fan la condici\u00f3n de cada individuo, junto a sesiones de acupuntura, masajes y tai chi que, al decir del equipo a cargo, fueron vitales para estabilizar la salud mental.\nYu Yanhong, dirigente de la Administraci\u00f3n Nacional de la MTC, inform\u00f3 que 74 mil 187 pacientes recibieron una mezcla de tratamientos naturales con los occidentales durante la observaci\u00f3n, las etapas leve, moderada y cr\u00edtica de la enfermedad, y tras el alta m\u00e9dica.\nSeg\u00fan detall\u00f3, en 91,91 por ciento se observ\u00f3 un fortalecimiento del sistema inmunol\u00f3gico, efectos antiinflamatorios, la eliminaci\u00f3n del virus en menor tiempo y una recuperaci\u00f3n sin reca\u00edda.\nOtro dato relevante fue la regeneraci\u00f3n, estimulaci\u00f3n y normal funcionamiento de \u00f3rganos internos como los pulmones, el h\u00edgado y los ri\u00f1ones, los cuales sufren da\u00f1o severo cuando el coronavirus invade el cuerpo humano.\nEl porcentaje restante de los enfermos mejor\u00f3 tambi\u00e9n y completaron las terapias en los hospitales designados para atender la afecci\u00f3n respiratoria.\nXu Guihua, especialista en el tema del hospital Shuguang de Shangh\u00e1i, explic\u00f3 la evoluci\u00f3n de la siguiente manera:\n\"Las enfermedades primero atacan al sistema inmunol\u00f3gico o el qi, como se denomina a la energ\u00eda que fluye por el cuerpo. La experiencia ganada en a\u00f1os evidenci\u00f3 que una buena combinaci\u00f3n de la medicina occidental y la MTC es una gran ventaja para combatir padecimientos infecciosos\", coment\u00f3 en un programa radial.\nAntes China integr\u00f3 las fortalezas de ambas variantes de la medicina frente a la epidemia del s\u00edndrome respiratorio agudo severo en 2002-03 y las distintas oleadas de la gripe aviar.\nBajo un enfoque preventivo, las autoridades distribuyeron f\u00f3rmulas naturales entre los obreros desplegados en obras de la construcci\u00f3n durante la reciente contingencia por la Covid-19.\nIncluso la noticia hizo que se agotara en las farmacias y tiendas por internet el anticatarral Shuanghuanglian, compuesto por extracto de distintas hierbas; y en el peor de los casos algunos individuos aprovecharon el momento y promovieron recetas con supuestos poderes terap\u00e9uticos.\nLa MTC ya es parte del protocolo de prevenci\u00f3n, control y tratamiento de la Covid-19 en China y ahora el pa\u00eds comparte con la comunidad internacional los resultados de su aplicaci\u00f3n.\nProfesionales en la materia integran las misiones del gigante asi\u00e1tico enviadas al exterior en apoyo a la batalla contra esa pandemia.\nAnalistas ven tambi\u00e9n una oportunidad estrat\u00e9gica en el aspecto econ\u00f3mico y no descartan un eventual auge en las exportaciones de productos de MTC, si gana aceptaci\u00f3n en el mercado global, especialmente en Asia.\nEse rubro muestra un crecimiento sostenido desde que Beijing se uni\u00f3 a la Organizaci\u00f3n Mundial del Comercio en 2001 y cerr\u00f3 2018 con env\u00edos de cuatro mil millones de d\u00f3lares, un alza interanual de 7,39 por ciento, indican cifras oficiales.\nDesde su surgimiento varios siglos atr\u00e1s, la medicina y la farmacolog\u00eda tradicionales de China contribuyeron a su prosperidad y tambi\u00e9n al progreso de la civilizaci\u00f3n mundial mientras cambian las concepciones sobre el bienestar f\u00edsico-mental.\nSu esencia es la armon\u00eda sobre la salud humana, o sea, el equilibrio din\u00e1mico entre las llamadas fuerzas opuestas el ying y el yang, y es considerado un tesoro de la cultura nacional por teor\u00edas y m\u00e9todos \u00fanicos.\nDesde la fundaci\u00f3n del pa\u00eds como rep\u00fablica en 1949, el gobierno chino apoya el desarrollo de la MTC y complementa su aplicaci\u00f3n con procedimientos occidentales a fin de fortalecer la seguridad sanitaria de la poblaci\u00f3n y al mismo tiempo revertir el escepticismo sobre esa forma de sanaci\u00f3n.\nPor ejemplo, una ley de 2016 contempl\u00f3 la apertura de cl\u00ednicas en hospitales generales y centros de atenci\u00f3n materno-infantil financiados con fondos p\u00fablicos y orden\u00f3 la debida calificaci\u00f3n de los practicantes.\nPlantea el uso de la tecnolog\u00eda, una protecci\u00f3n especial para f\u00f3rmulas consideradas secretos de Estado y de los recursos medicinales, lo cual implica el cultivo sin pesticidas t\u00f3xicos de especies raras y en peligro de extinci\u00f3n, y la supervisi\u00f3n de las materias primas.\nEllo est\u00e1 a tono con la selecci\u00f3n de la MTC como componente esencial del plan dise\u00f1ado para mejorar la salud del pueblo chino hacia 2030.\nYolaidy Mart\u00ednez, Corresponsal jefa de Prensa Latina en China\nPrensa Latina especial para Di\u00e1logos del Sur - Derechos reservados\nLas opiniones expresadas en este art\u00edculo no reflejan necesariamente la opini\u00f3n de Di\u00e1logos del Sur", "language": null, "image": "https://s3.operamundi.uol.com.br/thumb/dee1bd1a51b7f57f08096db7595646d0_76e011f020a956b2a62e921e1ee165b3.jpg", "pagetype": "article", "links": ["//operamundi.uol.com.br", "//dialogosdelsur.operamundi.uol.com.br", "//dialogosdelsur.operamundi.uol.com.br", "https://www.facebook.com/DialogosDelSur/", "javascript:void(0);", "https://dialogosdelsur.operamundi.uol.com.br/brasil", "https://dialogosdelsur.operamundi.uol.com.br/america-latina", "https://dialogosdelsur.operamundi.uol.com.br/derechos-humanos", "https://dialogosdelsur.operamundi.uol.com.br/mundo", "https://dialogosdelsur.operamundi.uol.com.br/medio-ambiente", "https://dialogosdelsur.operamundi.uol.com.br/economia", "https://dialogosdelsur.operamundi.uol.com.br/cultura", "https://dialogosdelsur.operamundi.uol.com.br/especial", "//catarse.me/dialogosdosul", "/salud", "https://twitter.com/intent/tweet?url=https%3A%2F%2Fdialogosdelsur.operamundi.uol.com.br%2Fpermalink%2F63977%3Fv%3D1.3%26l%3D63977&text=Resultados+positivos+revalorizan+la+medicina+tradicional+china+frente+a+Covid-19", "https://www.facebook.com/sharer/sharer.php?u=https%3A%2F%2Fdialogosdelsur.operamundi.uol.com.br%2Fpermalink%2F63977", "//api.whatsapp.com/send?text=Resultados+positivos+revalorizan+la+medicina+tradicional+china+frente+a+Covid-19+https%3A%2F%2Fdialogosdelsur.operamundi.uol.com.br%2Fpermalink%2F63977", "mailto:?subject=Resultados%20positivos%20revalorizan%20la%20medicina%20tradicional%20china%20frente%20a%20Covid-19&body=La MTC ya es parte del protocolo de prevenci\u00f3n, control y tratamiento de la Covid-19 en China y ahora el pa\u00eds comparte con la comunidad internacional https://dialogosdelsur.operamundi.uol.com.br/permalink/63977", "https://dialogosdelsur.operamundi.uol.com.br/autores/5593/yolaidy-martinez", "//prensa-latina.cu/", "/news?city_id=283", "https://dialogosdelsur.operamundi.uol.com.br/mundo", "https://dialogosdelsur.operamundi.uol.com.br/cultura", "https://dialogosdelsur.operamundi.uol.com.br/salud", "//www.catarse.me/dialogosdosul", "https://www.facebook.com/DialogosDelSur/", "/mundo", "https://twitter.com/intent/tweet?url=https%3A%2F%2Fdialogosdelsur.operamundi.uol.com.br%2Fpermalink%2F76460%3Fv%3D1.3%26l%3D76460&text=Muere+Mijail+Gorbachov%2C+el+%C3%BAltimo+presidente+de+la+Uni%C3%B3n+de+Rep%C3%BAblicas+Socialistas+Sovi%C3%A9ticas", "https://www.facebook.com/sharer/sharer.php?u=https%3A%2F%2Fdialogosdelsur.operamundi.uol.com.br%2Fpermalink%2F76460", "//api.whatsapp.com/send?text=Muere+Mijail+Gorbachov%2C+el+%C3%BAltimo+presidente+de+la+Uni%C3%B3n+de+Rep%C3%BAblicas+Socialistas+Sovi%C3%A9ticas+https%3A%2F%2Fdialogosdelsur.operamundi.uol.com.br%2Fpermalink%2F76460", "mailto:?subject=Muere%20Mijail%20Gorbachov%2C%20el%20%C3%BAltimo%20presidente%20de%20la%20Uni%C3%B3n%20de%20Rep%C3%BAblicas%20Socialistas%20Sovi%C3%A9ticas&body=Para unos Gorbachov traicion\u00f3 la causa del socialismo, es culpable de la desintegraci\u00f3n de la URSS y es el ingenuo que crey\u00f3 que la OTAN nunca se iba a expandir \"ni un cent\u00edmetro\" hacia el este. https://dialogosdelsur.operamundi.uol.com.br/permalink/76460", "https://dialogosdelsur.operamundi.uol.com.br/autores/5972/juan-pablo-duch", "//www.jornada.com.mx/", "/news?city_id=105", "https://dialogosdelsur.operamundi.uol.com.br/mundo", "//www.catarse.me/dialogosdosul", "https://www.facebook.com/DialogosDelSur/", "#", "#", "https://dialogosdelsur.operamundi.uol.com.br/brasil", "https://dialogosdelsur.operamundi.uol.com.br/america-latina", "https://dialogosdelsur.operamundi.uol.com.br/derechos-humanos", "https://dialogosdelsur.operamundi.uol.com.br/mundo", "https://dialogosdelsur.operamundi.uol.com.br/medio-ambiente", "https://dialogosdelsur.operamundi.uol.com.br/economia", "https://dialogosdelsur.operamundi.uol.com.br/cultura", "https://dialogosdelsur.operamundi.uol.com.br/especial", "https://www.facebook.com/DialogosDelSur/", "javascript:void(0);", "/apoye-esta-idea", "/editorial-los-desnorteados", "/expediente", "/contacto", "//arpadesign.com.br/"]}