{"title": "Holofit Ayurveda Gokshura 50C\u00e1ps - Farmacia Ciudad Lineal Dolores Ropa", "author": null, "url": "https://www.farmaciaciudadlinealdoloresropa.es/holofit-ayurveda-gokshura-50caps/", "hostname": "farmaciaciudadlinealdoloresropa.es", "description": "Holofit Ayurveda gokshura es un complemento alimenticio que ayuda a estimular la libido. Gracias a s...", "sitename": "Farmacia Ciudad Lineal Dolores Ropa", "date": "2022-11-03", "id": null, "license": null, "body": null, "comments": "", "commentsbody": null, "raw_text": null, "text": "Descripci\u00f3n\nHolofit Ayurveda gokshura es un complemento alimenticio que ayuda a estimular la libido. Gracias a su formulaci\u00f3n act\u00faa como estimulante de la testosterona y aumenta la libido en el hombre y en la mujer.\nSus principios activos contribuyen en el aumento de la resistencia y la musculaci\u00f3n al mismo tiempo que proporcionan vigor y enegr\u00eda.\n*No tomar mujeres embarazadas.\n\u00a1Refuerza tu organismo!\nModo de empleo\nTomar 1-2 c\u00e1psulas al d\u00eda, preferiblemente por las ma\u00f1anas.\nComposici\u00f3n\nEXTRACTO SECO DE ABROJO.", "language": null, "image": null, "pagetype": "article", "links": ["https://www.farmaciaciudadlinealdoloresropa.es/", "https://www.farmaciaciudadlinealdoloresropa.es/parafarmacia-online/", "https://www.farmaciaciudadlinealdoloresropa.es/", "https://www.farmaciaciudadlinealdoloresropa.es/parafarmacia-online/", "https://www.farmaciaciudadlinealdoloresropa.es/", "https://www.farmaciaciudadlinealdoloresropa.es/parafarmacia-online/", "https://www.farmaciaciudadlinealdoloresropa.es/", "https://www.farmaciaciudadlinealdoloresropa.es/parafarmacia-online/", "#", "https://farmaciaciudadlinealdoloresropa.es/mi-cuenta/", "https://www.farmaciaciudadlinealdoloresropa.es", "https://www.farmaciaciudadlinealdoloresropa.es/salud/", "https://www.farmaciaciudadlinealdoloresropa.es/salud-sexual/", "https://www.farmaciaciudadlinealdoloresropa.es/vigorizantes/", "https://www.farmaciaciudadlinealdoloresropa.es/unisex-vigorizantes/", "https://www.farmaciaciudadlinealdoloresropa.es/wp-content/uploads/2022/11/8436003023760-1.jpg", "https://www.farmaciaciudadlinealdoloresropa.es/unisex-vigorizantes/", "https://www.farmaciaciudadlinealdoloresropa.es/marca/holofit/", "#tab-description", "https://www.farmaciaciudadlinealdoloresropa.es/el-oro-de-los-andes-maca-negra-ecologica-90-capsulas/", "https://www.farmaciaciudadlinealdoloresropa.es/el-oro-de-los-andes-maca-negra-ecologica-90-capsulas/", "https://www.farmaciaciudadlinealdoloresropa.es/el-oro-de-los-andes-maca-roja-700-mg-90-capsulas/", "https://www.farmaciaciudadlinealdoloresropa.es/el-oro-de-los-andes-maca-roja-700-mg-90-capsulas/", "https://www.farmaciaciudadlinealdoloresropa.es/robis-maca-forte-megadosis-5000mg-60caps/", "https://www.farmaciaciudadlinealdoloresropa.es/robis-maca-forte-megadosis-5000mg-60caps/", "https://www.farmaciaciudadlinealdoloresropa.es/aspolvit-vigor-30comp/", "?add-to-cart=3968", "https://www.farmaciaciudadlinealdoloresropa.es/", "https://www.farmaciaciudadlinealdoloresropa.es/parafarmacia-online/", "https://www.farmaciaciudadlinealdoloresropa.es/", "https://www.farmaciaciudadlinealdoloresropa.es/parafarmacia-online/", "https://www.farmaciaciudadlinealdoloresropa.es/contacto/", "https://www.farmaciaciudadlinealdoloresropa.es/ayuda-medicamentos/", "https://www.farmaciaciudadlinealdoloresropa.es/tiempo-de-entrega-y-gastos-de-envio/", "https://www.farmaciaciudadlinealdoloresropa.es/formas-de-pago/", "https://www.farmaciaciudadlinealdoloresropa.es/cambios-y-devoluciones/", "https://www.boe.es/diario_boe/txt.php?id=BOE-A-2013-11728", "https://www.aemps.gob.es/cima/publico/home.html", "https://distafarma.aemps.es/farmacom/faces/inicio.xhtml", "https://www.comunidad.madrid/servicios/salud/compra-medicamentos-internet", "\u201dmailto:info@farmaciaciudadlinealdoloresropa.es\u201d", "mailto:dolores@farmaciaciudadlinealdoloresropa.es", "tel:914050115", "tel:603632504", "https://www.optimistseo.com/", "https://www.farmaciaciudadlinealdoloresropa.es/aviso-legal/", "https://www.farmaciaciudadlinealdoloresropa.es/politica-de-cookies/", "https://www.farmaciaciudadlinealdoloresropa.es/politica-de-privacidad/", "https://www.farmaciaciudadlinealdoloresropa.es/aviso-legal/", "https://www.farmaciaciudadlinealdoloresropa.es/politica-de-cookies/", "https://www.farmaciaciudadlinealdoloresropa.es/politica-de-privacidad/", "https://www.farmaciaciudadlinealdoloresropa.es", "#", "https://wordpress.org/plugins/gdpr-cookie-compliance/"]}